OS/Admin.py
OS/User.py
OS/__init__.py
OS/swan.py
SwanOS-0.1.5.dist-info/METADATA
SwanOS-0.1.5.dist-info/WHEEL
SwanOS-0.1.5.dist-info/top_level.txt
SwanOS-0.1.5.dist-info/RECORD
