Metadata-Version: 2.1
Name: SwanOS
Version: 0.1.5
Summary: A Very Simple Python OS
Home-page: UNKNOWN
Author-email: forsbergw82@gmail.com
License: UNKNOWN
Platform: UNKNOWN
Classifier: Programming Language :: Python :: 3
